setup.py
jz/__init__.py
jz.cache.egg-info/PKG-INFO
jz.cache.egg-info/SOURCES.txt
jz.cache.egg-info/dependency_links.txt
jz.cache.egg-info/namespace_packages.txt
jz.cache.egg-info/requires.txt
jz.cache.egg-info/top_level.txt
jz/cache/__init__.py
jz/cache/author.txt
jz/cache/cache.py
jz/cache/configure.zcml
jz/cache/interfaces.py
jz/cache/jz.cache-configure.zcml
jz/cache/property.py
jz/cache/readme.txt
jz/cache/tests/__init__.py
jz/cache/tests/isample.py
jz/cache/tests/sample.py
jz/cache/tests/test_cache.py
jz/cache/tests/test_property.py
