Metadata-Version: 1.0
Name: jz.cache
Version: 0.1
Summary: Cache utilties which store data in annotations.
Home-page: http://www.jellofishi.com/zope
Author: Gabi Shaar
Author-email: gabi@jbox-comp.com
License: GPL
Platform: UNKNOWN
